physics/__init__.py
physics/dynamics.py
physics/electricity_magnetism.py
physics/electrostatics.py
physics/friction_and_elasticy_forces.py
physics/geometrical_optics.py
physics/hydrostatics_aerostatics.py
physics/kinematics.py
physics/other.py
physics/thermodynamics.py
physics/waves_and_oscillations.py
physics_formulas_dominik-1.0.0.dist-info/METADATA
physics_formulas_dominik-1.0.0.dist-info/WHEEL
physics_formulas_dominik-1.0.0.dist-info/top_level.txt
physics_formulas_dominik-1.0.0.dist-info/RECORD
