Metadata-Version: 2.2
Name: physics-formulas-dominik
Version: 1.0.0
Summary: A package for physics formulas
Home-page: https://github.com/twoj_github/physics-formulas
Author: Dominik Pelc
Author-email: twojemail@example.com
Classifier: Programming Language :: Python :: 3
Classifier: License :: OSI Approved :: MIT License
Classifier: Operating System :: OS Independent
Requires-Python: >=3.6
Dynamic: author
Dynamic: author-email
Dynamic: classifier
Dynamic: description-content-type
Dynamic: home-page
Dynamic: requires-python
Dynamic: summary
